vcpkgpip/__main__.py
vcpkgpip-1.0.0.dist-info/LICENSE
vcpkgpip-1.0.0.dist-info/METADATA
vcpkgpip-1.0.0.dist-info/WHEEL
vcpkgpip-1.0.0.dist-info/entry_points.txt
vcpkgpip-1.0.0.dist-info/top_level.txt
vcpkgpip-1.0.0.dist-info/RECORD
