Metadata-Version: 2.1
Name: vcpkgpip
Version: 1.0.0
Summary: a python wrapper for vcpkg
Home-page: https://github.com/AlyShmahell/vcpkgpip
Author: Aly Shmahell
Author-email: 
License: UNKNOWN
Platform: UNKNOWN
